odoo9_addon_asterisk_click2dial-9.0.1.0.0.99.dev7-py2.7-nspkg.pth
odoo9_addon_asterisk_click2dial-9.0.1.0.0.99.dev7.dist-info/DESCRIPTION.rst
odoo9_addon_asterisk_click2dial-9.0.1.0.0.99.dev7.dist-info/METADATA
odoo9_addon_asterisk_click2dial-9.0.1.0.0.99.dev7.dist-info/RECORD
odoo9_addon_asterisk_click2dial-9.0.1.0.0.99.dev7.dist-info/WHEEL
odoo9_addon_asterisk_click2dial-9.0.1.0.0.99.dev7.dist-info/metadata.json
odoo9_addon_asterisk_click2dial-9.0.1.0.0.99.dev7.dist-info/namespace_packages.txt
odoo9_addon_asterisk_click2dial-9.0.1.0.0.99.dev7.dist-info/top_level.txt
odoo_addons/asterisk_click2dial/__init__.py
odoo_addons/asterisk_click2dial/__openerp__.py
odoo_addons/asterisk_click2dial/asterisk_click2dial.py
odoo_addons/asterisk_click2dial/asterisk_click2dial_demo.xml
odoo_addons/asterisk_click2dial/asterisk_server_view.xml
odoo_addons/asterisk_click2dial/controller.py
odoo_addons/asterisk_click2dial/requirements.txt
odoo_addons/asterisk_click2dial/res_users_view.xml
odoo_addons/asterisk_click2dial/web_asterisk_click2dial.xml
odoo_addons/asterisk_click2dial/i18n/bg.po
odoo_addons/asterisk_click2dial/i18n/es.po
odoo_addons/asterisk_click2dial/i18n/fr.po
odoo_addons/asterisk_click2dial/i18n/hr.po
odoo_addons/asterisk_click2dial/i18n/pt_BR.po
odoo_addons/asterisk_click2dial/scripts/openerp_popup_timeout.sh
odoo_addons/asterisk_click2dial/scripts/set_name_agi.py
odoo_addons/asterisk_click2dial/scripts/set_name_incoming_timeout.sh
odoo_addons/asterisk_click2dial/scripts/set_name_outgoing_timeout.sh
odoo_addons/asterisk_click2dial/security/ir.model.access.csv
odoo_addons/asterisk_click2dial/static/description/icon.png
odoo_addons/asterisk_click2dial/static/description/sshot-click2dial.jpg
odoo_addons/asterisk_click2dial/static/description/sshot-open_calling_party.jpg
odoo_addons/asterisk_click2dial/static/src/css/asterisk_click2dial.css
odoo_addons/asterisk_click2dial/static/src/js/asterisk_click2dial.js
odoo_addons/asterisk_click2dial/static/src/xml/asterisk_click2dial.xml
